audio_extract/__init__.py
audio_extract/execute.py
audio_extract/ffmpeg.py
audio_extract/utils.py
audio_extract/validators.py
audio_extract-0.7.0.dist-info/LICENSE.md
audio_extract-0.7.0.dist-info/METADATA
audio_extract-0.7.0.dist-info/WHEEL
audio_extract-0.7.0.dist-info/entry_points.txt
audio_extract-0.7.0.dist-info/top_level.txt
audio_extract-0.7.0.dist-info/RECORD
