Metadata-Version: 2.1
Name: audio_extract
Version: 0.7.0
Summary: Extract and trim audio from videos or trim audios.
Home-page: https://github.com/riad-azz/audio-extract
Author: riad-azz
Author-email: riadh.azzoun@hotmail.com
License: MIT License
Project-URL: Source, https://github.com/riad-azz/audio-extract
Keywords: convert video,audio,ffmpeg,video to mp3
Classifier: Development Status :: 5 - Production/Stable
Classifier: Intended Audience :: Developers
Classifier: Natural Language :: English
Classifier: Programming Language :: Python :: 3.11
Classifier: License :: OSI Approved :: MIT License
Classifier: Operating System :: OS Independent
Classifier: Topic :: Multimedia
Classifier: Topic :: Multimedia :: Sound/Audio
Classifier: Topic :: Multimedia :: Video
Classifier: Topic :: Multimedia :: Video :: Conversion
License-File: LICENSE.md
Requires-Dist: ffmpeg-python==0.2.0
Requires-Dist: imageio-ffmpeg==0.4.8
Requires-Dist: mutagen==1.46.0
